wily/__init__.py
wily/__main__.py
wily/cache.py
wily/config.py
wily/decorators.py
wily/lang.py
wily/state.py
wily/archivers/__init__.py
wily/archivers/filesystem.py
wily/archivers/git.py
wily/commands/__init__.py
wily/commands/build.py
wily/commands/diff.py
wily/commands/graph.py
wily/commands/index.py
wily/commands/list_metrics.py
wily/commands/rank.py
wily/commands/report.py
wily/helper/__init__.py
wily/helper/custom_enums.py
wily/locales/messages.pot
wily/locales/de/LC_MESSAGES/messages.mo
wily/locales/de/LC_MESSAGES/messages.po
wily/locales/en/LC_MESSAGES/messages.mo
wily/locales/en/LC_MESSAGES/messages.po
wily/locales/en_AU/LC_MESSAGES/messages.mo
wily/locales/en_AU/LC_MESSAGES/messages.po
wily/locales/ja/LC_MESSAGES/messages.mo
wily/locales/ja/LC_MESSAGES/messages.po
wily/operators/__init__.py
wily/operators/cyclomatic.py
wily/operators/halstead.py
wily/operators/maintainability.py
wily/operators/raw.py
wily/templates/report_template.html
wily/templates/css/main.css
wily-1.24.2.dist-info/entry_points.txt
wily-1.24.2.dist-info/LICENSE
wily-1.24.2.dist-info/WHEEL
wily-1.24.2.dist-info/METADATA
wily-1.24.2.dist-info/RECORD
