Metadata-Version: 2.1
Name: wily
Version: 1.24.2
Summary: A Python application for tracking, reporting on timing and complexity in tests and applications.
Author-email: Anthony Shaw <anthonyshaw@apache.org>
Requires-Python: >=3.6
Classifier: License :: OSI Approved :: Apache Software License
Classifier: Development Status :: 5 - Production/Stable
Classifier: Intended Audience :: Developers
Classifier: Programming Language :: Python :: 3.6
Classifier: Programming Language :: Python :: 3.7
Classifier: Programming Language :: Python :: 3.8
Classifier: Programming Language :: Python :: 3.9
Classifier: Programming Language :: Python :: 3.10
Classifier: Programming Language :: Python :: 3.11
Classifier: Programming Language :: Python :: 3 :: Only
Requires-Dist: gitpython>=3.0.0,<4.0.0
Requires-Dist: radon>=5.1,<5.2
Requires-Dist: click>=7.0,<9.0
Requires-Dist: nbformat>=5.1.3,<6.0.0
Requires-Dist: colorlog>=4.0.0,<5.0.0
Requires-Dist: tabulate>=0.8.2,<1.0.0
Requires-Dist: plotly>=4.0.0,<6.0.0
Requires-Dist: progress>=1.4,<2.0
Requires-Dist: dataclasses; python_version == '3.6'
Requires-Dist: bandit~=1.7.4 ; extra == "dev"
Requires-Dist: black~=22.6.0 ; extra == "dev"
Requires-Dist: codespell~=2.1.0 ; extra == "dev"
Requires-Dist: flake8~=4.0.1 ; extra == "dev"
Requires-Dist: flake8-bugbear~=22.7.1 ; extra == "dev"
Requires-Dist: flake8-comprehensions~=3.10.0 ; extra == "dev"
Requires-Dist: flake8-2020~=1.6.1 ; extra == "dev"
Requires-Dist: isort~=5.10.1 ; extra == "dev"
Requires-Dist: mypy~=0.961 ; extra == "dev"
Requires-Dist: pydocstyle~=6.1.1 ; extra == "dev"
Requires-Dist: pyupgrade~=2.37.1 ; extra == "dev"
Requires-Dist: safety~=2.3.4 ; extra == "dev"
Requires-Dist: pytest~=7.2 ; extra == "test"
Requires-Dist: pytest-cov~=3.0.0 ; extra == "test"
Project-URL: Documentation, https://wily.readthedocs.io/en/latest/
Project-URL: Homepage, https://github.com/tonybaloney/wily
Provides-Extra: dev
Provides-Extra: doc
Provides-Extra: test
